psql2py/__main__.py
psql2py/common.py
psql2py/generate.py
psql2py/inspect.py
psql2py/load.py
psql2py/render.py
psql2py/templates/module.py.jinja
psql2py/types.py
psql2py-0.2.0.dist-info/WHEEL
psql2py-0.2.0.dist-info/METADATA
psql2py-0.2.0.dist-info/RECORD
